odoo/addons/stock_forecast_report/README.rst
odoo/addons/stock_forecast_report/__init__.py
odoo/addons/stock_forecast_report/__manifest__.py
odoo/addons/stock_forecast_report/i18n/it.po
odoo/addons/stock_forecast_report/i18n/stock_forecast_report.pot
odoo/addons/stock_forecast_report/readme/CONTRIBUTORS.rst
odoo/addons/stock_forecast_report/readme/DESCRIPTION.rst
odoo/addons/stock_forecast_report/readme/ROADMAP.rst
odoo/addons/stock_forecast_report/readme/USAGE.rst
odoo/addons/stock_forecast_report/reports/__init__.py
odoo/addons/stock_forecast_report/reports/report_stock_quantity.py
odoo/addons/stock_forecast_report/reports/report_stock_quantity.xml
odoo/addons/stock_forecast_report/security/ir.model.access.csv
odoo/addons/stock_forecast_report/static/description/icon.png
odoo/addons/stock_forecast_report/static/description/index.html
odoo/addons/stock_forecast_report/static/description/screenshot_stock_forecast.png
odoo/addons/stock_forecast_report/tests/__init__.py
odoo/addons/stock_forecast_report/tests/test_report_stock_quantity.py
odoo12_addon_stock_forecast_report-12.0.1.0.0.99.dev10.dist-info/METADATA
odoo12_addon_stock_forecast_report-12.0.1.0.0.99.dev10.dist-info/WHEEL
odoo12_addon_stock_forecast_report-12.0.1.0.0.99.dev10.dist-info/top_level.txt
odoo12_addon_stock_forecast_report-12.0.1.0.0.99.dev10.dist-info/RECORD
